protoc_gen_pyproject/__init__.py
protoc_gen_pyproject/__main__.py
protoc_gen_pyproject/main.py
protoc_gen_pyproject/parser.py
protoc_gen_pyproject-0.3.2.dist-info/LICENSE
protoc_gen_pyproject-0.3.2.dist-info/METADATA
protoc_gen_pyproject-0.3.2.dist-info/WHEEL
protoc_gen_pyproject-0.3.2.dist-info/entry_points.txt
protoc_gen_pyproject-0.3.2.dist-info/top_level.txt
protoc_gen_pyproject-0.3.2.dist-info/RECORD
